foxtail/__init__.py
foxtail/__main__.py
foxtail-1.0.0.dist-info/METADATA
foxtail-1.0.0.dist-info/WHEEL
foxtail-1.0.0.dist-info/RECORD
