Metadata-Version: 2.1
Name: foxtail
Version: 1.0.0
Summary: 
Author: BlakeJC94
Author-email: blakejamescook@gmail.com
Requires-Python: >=3.10,<4.0
Classifier: Programming Language :: Python :: 3
Classifier: Programming Language :: Python :: 3.10
Classifier: Programming Language :: Python :: 3.11
Classifier: Programming Language :: Python :: 3.12
